{
  "required": true,
  "minVersion": "0.8",
  "package": "io.github.merchantpug.cursedorigins.mixin",
  "compatibilityLevel": "JAVA_16",
  "mixins": [
    "BedBlockMixin",
    "CreeperEntityMixin",
    "DamageSourceMixin",
    "EggEntityMixin",
    "EndCrystalEntityMixin",
    "EnderPearlEntityMixin",
    "ExplosionMixin",
    "FireballEntityMixin",
    "FireworkRocketEntityMixin",
    "LivingEntityMixin",
    "PersistentProjectileEntityMixin",
    "PlayerEntityMixin",
    "RespawnAnchorBlockMixin",
    "SkeletonEntityMixin",
    "SnowballEntityMixin",
    "StatusEffectMixin",
    "TntEntityMixin",
    "TridentEntityMixin",
    "WitherSkeletonEntityMixin",
    "ZombieEntityMixin"
  ],
  "injectors": {
    "defaultRequire": 1
  }
}
